pyseldonlib/_basemodel.py
pyseldonlib/ActivityDrivenModel.py
pyseldonlib/InertialModel.py
pyseldonlib/__init__.py
pyseldonlib/_run_simulation.py
pyseldonlib/utils.py
pyseldonlib/network.py
pyseldonlib/_othersettings.py
pyseldonlib/DeGrootModel.py
pyseldonlib/DeffuantVectorModel.py
pyseldonlib/DeffuantModel.py
bindings/seldoncore.cpython-311-darwin.so
pyseldonlib-1.0.0.dist-info/RECORD
pyseldonlib-1.0.0.dist-info/WHEEL
pyseldonlib-1.0.0.dist-info/METADATA
