Metadata-Version: 2.1
Name: pyseldonlib
Version: 1.0.0
Summary: Python Bindings for the Seldon Framework
Keywords: Seldon-Code,Seldon,Opinion Dynamics,Opinion Dynamics Simulation,Social Influence,Social Dynamics,DeGroot Model,Inertial Model,Activity Driven Model,Deffuant Model,Deffuant Vector Model
Author-Email: Daivik Karbhari <daivikkarbhari01@gmail.com>
Maintainer-Email: Amrita Goswami <amrita16thaug646@gmail.com>, Daivik Karbhari <daivikkarbhari01@gmail.com>, Moritz Sallermann <moritzsallermann@gmail.com>, Rohit Goswami <rgoswami@ieee.org>
License: GPL v3
Classifier: Development Status :: 4 - Beta
Classifier: Intended Audience :: Developers
Classifier: License :: OSI Approved :: GNU General Public License v3 (GPLv3)
Classifier: Programming Language :: Python
Classifier: Programming Language :: Python :: 3
Classifier: Programming Language :: Python :: 3.9
Classifier: Programming Language :: Python :: 3.10
Classifier: Programming Language :: Python :: 3.11
Classifier: Topic :: Software Development :: Libraries
Classifier: Topic :: Scientific/Engineering :: Mathematics
Project-URL: Source code, https://github.com/seldon-code/pyseldonlib
Project-URL: Documentation, https://seldon-code.github.io/pyseldonlib/
Requires-Python: >=3.9
Requires-Dist: pybind11>=2.12.0
